{
  "name": "Catppuccin Macchiato",
  "version": "1.0.0",
  "colorScheme": "dark",
  "colors": {
    "surface": "#24273a",
    "surface-alt": "#1e2030",
    "surface-dim": "#181926",
    "surface-raised": "#363a4f",
    "content": "#cad3f5",
    "content-secondary": "#b8c0e0",
    "content-muted": "#8087a2",
    "content-inverse": "#24273a",
    "edge": "#363a4f",
    "edge-subtle": "#1e2030",
    "edge-strong": "#5b6078",
    "accent": "#c6a0f6",
    "accent-hover": "#d0b0f8",
    "accent-alt": "#8bd5ca",
    "success": "#a6da95",
    "warning": "#eed49f",
    "danger": "#ed8796",
    "pending": "#f5a97f",
    "key-bg": "#1e2030",
    "key-bg-hover": "#363a4f",
    "key-bg-active": "#c6a0f6",
    "key-border": "#494d64",
    "key-shadow": "#181926",
    "key-label": "#cad3f5",
    "key-sublabel": "#8087a2",
    "key-label-remap": "#f5a97f",
    "key-bg-multi-selected": "#3c3d5c",
    "tab-bg-active": "#c6a0f6",
    "tab-text": "#6e738d",
    "tab-text-active": "#cad3f5",
    "picker-bg": "#181926",
    "picker-item-bg": "#24273a",
    "picker-item-hover": "#1e2030",
    "picker-item-text": "#cad3f5",
    "picker-item-border": "#363a4f"
  }
}
